dbtunnel/__init__.py
dbtunnel/arize_phoenix_ui.py
dbtunnel/bokeh.py
dbtunnel/chainlit.py
dbtunnel/code_server.py
dbtunnel/dash.py
dbtunnel/fastapi.py
dbtunnel/flask.py
dbtunnel/gradio.py
dbtunnel/ngrok.py
dbtunnel/nicegui.py
dbtunnel/ray.py
dbtunnel/shiny.py
dbtunnel/solara.py
dbtunnel/stable_diffusion_ui.py
dbtunnel/streamlit.py
dbtunnel/tunnels.py
dbtunnel/utils.py
dbtunnel/uvicorn.py
dbtunnel/cli/__init__.py
dbtunnel/cli/cli.py
dbtunnel/relay/__init__.py
dbtunnel/vendor/__init__.py
dbtunnel/vendor/asgiproxy/__init__.py
dbtunnel/vendor/asgiproxy/__main__.py
dbtunnel/vendor/asgiproxy/base.py
dbtunnel/vendor/asgiproxy/config.py
dbtunnel/vendor/asgiproxy/context.py
dbtunnel/vendor/asgiproxy/frameworks.py
dbtunnel/vendor/asgiproxy/simple_proxy.py
dbtunnel/vendor/asgiproxy/proxies/__init__.py
dbtunnel/vendor/asgiproxy/proxies/http.py
dbtunnel/vendor/asgiproxy/proxies/websocket.py
dbtunnel/vendor/asgiproxy/templates/__init__.py
dbtunnel/vendor/asgiproxy/templates/login.html
dbtunnel/vendor/asgiproxy/utils/__init__.py
dbtunnel/vendor/asgiproxy/utils/headers.py
dbtunnel/vendor/asgiproxy/utils/streams.py
dbtunnel-0.16.0.dist-info/LICENSE
dbtunnel-0.16.0.dist-info/METADATA
dbtunnel-0.16.0.dist-info/WHEEL
dbtunnel-0.16.0.dist-info/entry_points.txt
dbtunnel-0.16.0.dist-info/top_level.txt
dbtunnel-0.16.0.dist-info/RECORD
