Metadata-Version: 2.1
Name: dbtunnel
Version: 0.16.0
Summary: Run app and get cluster proxy url for it in databricks clusters
Home-page: https://github.com/stikkireddy/dbtunnel
Author: Sri Tikkireddy
Author-email: sri.tikkireddy@databricks.com
Classifier: Programming Language :: Python :: 3
Classifier: License :: OSI Approved :: MIT License
Classifier: Operating System :: OS Independent
Requires-Python: >=3.10
License-File: LICENSE
Requires-Dist: nest-asyncio
Requires-Dist: databricks-sdk >=0.18.0
Provides-Extra: arize-phoenix
Requires-Dist: arize-phoenix ; extra == 'arize-phoenix'
Provides-Extra: asgiproxy
Requires-Dist: aiohttp ; extra == 'asgiproxy'
Requires-Dist: starlette ; extra == 'asgiproxy'
Requires-Dist: uvicorn ; extra == 'asgiproxy'
Requires-Dist: websockets ; extra == 'asgiproxy'
Requires-Dist: python-multipart ; extra == 'asgiproxy'
Requires-Dist: cachetools ; extra == 'asgiproxy'
Provides-Extra: bokeh
Requires-Dist: bokeh ; extra == 'bokeh'
Provides-Extra: chainlit
Requires-Dist: chainlit ; extra == 'chainlit'
Requires-Dist: uvicorn ; extra == 'chainlit'
Provides-Extra: cli
Requires-Dist: click ; extra == 'cli'
Provides-Extra: dash
Requires-Dist: dash ; extra == 'dash'
Requires-Dist: fastapi ; extra == 'dash'
Requires-Dist: uvicorn ; extra == 'dash'
Provides-Extra: dev
Requires-Dist: mkdocs-material ; extra == 'dev'
Requires-Dist: mkdocs-jupyter ; extra == 'dev'
Provides-Extra: fastapi
Requires-Dist: fastapi ; extra == 'fastapi'
Requires-Dist: uvicorn ; extra == 'fastapi'
Provides-Extra: flask
Requires-Dist: flask ; extra == 'flask'
Requires-Dist: fastapi ; extra == 'flask'
Requires-Dist: uvicorn ; extra == 'flask'
Provides-Extra: gradio
Requires-Dist: gradio ==3.50.2 ; extra == 'gradio'
Provides-Extra: ngrok
Requires-Dist: pyngrok ; extra == 'ngrok'
Requires-Dist: ngrok-api ; extra == 'ngrok'
Requires-Dist: requests ; extra == 'ngrok'
Provides-Extra: nicegui
Requires-Dist: nicegui ; extra == 'nicegui'
Provides-Extra: ray
Requires-Dist: ray ; extra == 'ray'
Requires-Dist: fastapi ; extra == 'ray'
Provides-Extra: shiny
Requires-Dist: shiny ; extra == 'shiny'
Provides-Extra: solara
Requires-Dist: solara ; extra == 'solara'
Provides-Extra: sql
Requires-Dist: databricks-sql-connector ; extra == 'sql'
Provides-Extra: streamlit
Requires-Dist: streamlit ; extra == 'streamlit'
Requires-Dist: pyarrow >=11 ; extra == 'streamlit'
Provides-Extra: uvicorn
Requires-Dist: uvicorn ; extra == 'uvicorn'
